README.md
setup.py
Tea/__init__.py
Tea/converter.py
Tea/core.py
Tea/exceptions.py
Tea/model.py
Tea/request.py
Tea/response.py
Tea/stream.py
Tea/vendored/__init__.py
Tea/vendored/requests/__init__.py
Tea/vendored/requests/__version__.py
Tea/vendored/requests/_internal_utils.py
Tea/vendored/requests/adapters.py
Tea/vendored/requests/api.py
Tea/vendored/requests/auth.py
Tea/vendored/requests/certs.py
Tea/vendored/requests/compat.py
Tea/vendored/requests/cookies.py
Tea/vendored/requests/exceptions.py
Tea/vendored/requests/help.py
Tea/vendored/requests/hooks.py
Tea/vendored/requests/models.py
Tea/vendored/requests/packages.py
Tea/vendored/requests/sessions.py
Tea/vendored/requests/status_codes.py
Tea/vendored/requests/structures.py
Tea/vendored/requests/utils.py
Tea/vendored/requests/packages/__init__.py
Tea/vendored/requests/packages/certifi/__init__.py
Tea/vendored/requests/packages/certifi/__main__.py
Tea/vendored/requests/packages/certifi/cacert.pem
Tea/vendored/requests/packages/certifi/core.py
Tea/vendored/requests/packages/chardet/__init__.py
Tea/vendored/requests/packages/chardet/big5freq.py
Tea/vendored/requests/packages/chardet/big5prober.py
Tea/vendored/requests/packages/chardet/chardistribution.py
Tea/vendored/requests/packages/chardet/charsetgroupprober.py
Tea/vendored/requests/packages/chardet/charsetprober.py
Tea/vendored/requests/packages/chardet/codingstatemachine.py
Tea/vendored/requests/packages/chardet/compat.py
Tea/vendored/requests/packages/chardet/cp949prober.py
Tea/vendored/requests/packages/chardet/enums.py
Tea/vendored/requests/packages/chardet/escprober.py
Tea/vendored/requests/packages/chardet/escsm.py
Tea/vendored/requests/packages/chardet/eucjpprober.py
Tea/vendored/requests/packages/chardet/euckrfreq.py
Tea/vendored/requests/packages/chardet/euckrprober.py
Tea/vendored/requests/packages/chardet/euctwfreq.py
Tea/vendored/requests/packages/chardet/euctwprober.py
Tea/vendored/requests/packages/chardet/gb2312freq.py
alibabacloud_tea_py2.egg-info/PKG-INFO
alibabacloud_tea_py2.egg-info/SOURCES.txt
alibabacloud_tea_py2.egg-info/dependency_links.txt
alibabacloud_tea_py2.egg-info/top_level.txt